setup.py
odoo/addons/mail_activity_mail_template/CHANGELOG.md
odoo/addons/mail_activity_mail_template/README.rst
odoo/addons/mail_activity_mail_template/__init__.py
odoo/addons/mail_activity_mail_template/__manifest__.py
odoo/addons/mail_activity_mail_template/demo/mail_activity_type.xml
odoo/addons/mail_activity_mail_template/demo/mail_template.xml
odoo/addons/mail_activity_mail_template/models/__init__.py
odoo/addons/mail_activity_mail_template/models/mail_activity.py
odoo/addons/mail_activity_mail_template/static/description/icon.png
odoo/addons/mail_activity_mail_template/tests/__init__.py
odoo/addons/mail_activity_mail_template/tests/test_mail_activity.py
odoo/addons/mail_activity_mail_template/views/mail_activity_view.xml
odoo_addon_mail_activity_mail_template.egg-info/PKG-INFO
odoo_addon_mail_activity_mail_template.egg-info/SOURCES.txt
odoo_addon_mail_activity_mail_template.egg-info/dependency_links.txt
odoo_addon_mail_activity_mail_template.egg-info/not-zip-safe
odoo_addon_mail_activity_mail_template.egg-info/requires.txt
odoo_addon_mail_activity_mail_template.egg-info/top_level.txt